downloads/__init__.py
downloads/download.py
downloads-1.1.0.dist-info/LICENSE
downloads-1.1.0.dist-info/METADATA
downloads-1.1.0.dist-info/WHEEL
downloads-1.1.0.dist-info/RECORD
