Metadata-Version: 2.1
Name: downloads
Version: 1.1.0
Summary: Easy file downloads
License: MIT
Author: Austin Davis-Richardson
Author-email: accounts@agdr.org
Requires-Python: >=3.12,<4.0
Classifier: License :: OSI Approved :: MIT License
Classifier: Programming Language :: Python :: 3
Classifier: Programming Language :: Python :: 3.12
